data_plugin/__init__.py
data_plugin/cli.py
data_plugin-0.1.4.dist-info/METADATA
data_plugin-0.1.4.dist-info/WHEEL
data_plugin-0.1.4.dist-info/entry_points.txt
data_plugin-0.1.4.dist-info/top_level.txt
data_plugin-0.1.4.dist-info/RECORD
