Metadata-Version: 2.1
Name: data_plugin
Version: 0.1.4
Requires-Dist: typer
